plecos/__init__.py
plecos/plecos.py
plecos/validate_cli.py
plecos/samples/algorithm_metadata_local.json
plecos/samples/algorithm_metadata_remote.json
plecos/samples/metadata_local_broken.json
plecos/samples/sample_metadata_local.json
plecos/samples/sample_metadata_remote.json
plecos/samples/other/simple.json
plecos/samples/other/squid_example.json
plecos/samples/other/supersimple.json
plecos/samples/other/test.json
plecos/schemas/metadata_local_v0_4.json
plecos/schemas/metadata_local_v0_5.json
plecos/schemas/metadata_remote_v0_4.json
plecos/schemas/metadata_remote_v0_5.json
plecos/schemas/superceded/metadata_190118.json
plecos/schemas/superceded/metadata_190131.json
plecos/schemas/superceded/metadata_190218.json
plecos/schemas/superceded/metadata_local_190305.json
plecos/schemas/superceded/metadata_local_v0_1.json
plecos/schemas/superceded/metadata_local_v0_2.json
plecos/schemas/superceded/metadata_local_v0_3.json
plecos/schemas/superceded/metadata_local_v0_4.json
plecos/schemas/superceded/metadata_remote_190305.json
plecos/schemas/superceded/metadata_remote_v0_1.json
plecos/schemas/superceded/metadata_remote_v0_2.json
plecos/schemas/superceded/metadata_remote_v0_3.json
plecos/schemas/superceded/metadata_remote_v0_4.json
plecos-1.1.0.dist-info/LICENSE
plecos-1.1.0.dist-info/METADATA
plecos-1.1.0.dist-info/WHEEL
plecos-1.1.0.dist-info/top_level.txt
plecos-1.1.0.dist-info/RECORD
